{
  "/_not-found/page": "app/_not-found/page.js",
  "/activities/page": "app/activities/page.js",
  "/admin/page": "app/admin/page.js",
  "/flights/page": "app/flights/page.js",
  "/page": "app/page.js",
  "/transfers/page": "app/transfers/page.js",
  "/hotels/page": "app/hotels/page.js",
  "/api/activities/[activityId]/route": "app/api/activities/[activityId]/route.js",
  "/api/admin/bookings/route": "app/api/admin/bookings/route.js",
  "/api/admin/logs/route": "app/api/admin/logs/route.js",
  "/api/activities/search/route": "app/api/activities/search/route.js",
  "/api/admin/users/route": "app/api/admin/users/route.js",
  "/api/admin/stats/route": "app/api/admin/stats/route.js",
  "/api/flights/book/route": "app/api/flights/book/route.js",
  "/api/admin/config/route": "app/api/admin/config/route.js",
  "/api/flights/cheapest-dates/route": "app/api/flights/cheapest-dates/route.js",
  "/api/airlines/route": "app/api/airlines/route.js",
  "/api/flights/search/route": "app/api/flights/search/route.js",
  "/api/flights/orders/[orderId]/route": "app/api/flights/orders/[orderId]/route.js",
  "/api/flights/status/route": "app/api/flights/status/route.js",
  "/api/flights/pricing/route": "app/api/flights/pricing/route.js",
  "/api/hotels/autocomplete/route": "app/api/hotels/autocomplete/route.js",
  "/api/hotels/book/route": "app/api/hotels/book/route.js",
  "/api/hotels/offers/route": "app/api/hotels/offers/route.js",
  "/api/flights/seatmaps/route": "app/api/flights/seatmaps/route.js",
  "/api/transfers/cancel/route": "app/api/transfers/cancel/route.js",
  "/api/hotels/search/route": "app/api/hotels/search/route.js",
  "/api/transfers/book/route": "app/api/transfers/book/route.js",
  "/api/locations/route": "app/api/locations/route.js",
  "/api/transfers/search/route": "app/api/transfers/search/route.js"
}